pkrsplitter/__init__.py
pkrsplitter/settings.py
pkrsplitter/lambda/__init__.py
pkrsplitter/lambda/history_splitter.py
pkrsplitter/patterns/__init__.py
pkrsplitter/patterns/winamax.py
pkrsplitter/runs/__init__.py
pkrsplitter/runs/cloud/__init__.py
pkrsplitter/runs/cloud/correct_files.py
pkrsplitter/runs/cloud/split_files.py
pkrsplitter/runs/cloud/split_new_files.py
pkrsplitter/runs/cloud/split_new_histories.py
pkrsplitter/runs/local/__init__.py
pkrsplitter/runs/local/correct_files.py
pkrsplitter/runs/local/split_files.py
pkrsplitter/runs/local/split_new_files.py
pkrsplitter/runs/local/split_new_histories.py
pkrsplitter/splitters/__init__.py
pkrsplitter/splitters/abstract.py
pkrsplitter/splitters/cloud.py
pkrsplitter/splitters/local.py
pkrsplitter-1.1.4.dist-info/LICENSE.txt
pkrsplitter-1.1.4.dist-info/METADATA
pkrsplitter-1.1.4.dist-info/WHEEL
pkrsplitter-1.1.4.dist-info/top_level.txt
pkrsplitter-1.1.4.dist-info/RECORD
