Metadata-Version: 2.1
Name: pkrsplitter
Version: 1.1.4
Summary: A package to split poker history files
Home-page: https://github.com/manggy94/PokerSplitter
Author: Alexandre MANGWA
Author-email: alex.mangwa@gmail.com
License: UNKNOWN
Project-URL: Bug Tracker, https://github.com/manggy94//issues
Project-URL: Documentation, https://pkrsplitter.readthedocs.io/en/latest/
Platform: UNKNOWN
Classifier: Development Status :: 4 - Beta
Classifier: Intended Audience :: Developers
Classifier: License :: OSI Approved :: MIT License
Classifier: Natural Language :: English
Classifier: Programming Language :: Python
Classifier: Programming Language :: Python :: 3
Requires-Python: >=3.10
License-File: LICENSE.txt
Requires-Dist: python-dotenv
